<?xml version="1.0" encoding="UTF-8"?>
<forms version="0.1" nm="각서(미성년자)" imgfileNames="" date="20230725102543"><pdf><fileName>30100085.pdf</fileName><totalPage>1</totalPage></pdf><header /><body><page no="1" code="" mustRead="false" title=""><field name="AGT_ADDR_0" type="edit" displayFieldName="본적"><properties height="13.000" width="170.000" x="387.830" y="654.615" /><propertiesEx limitInput="0" backColor="255,255,255" encrypt="false" entry="false" hidden="false" expNum="1" font="굴림" fontColor="0,0,0" fontSize="11" guideLine="" halign="center" inputCtrl="1" mLine="true" maskChar="*" maskType="" maxLength="0" unit="0" readonly="false" valign="middle" correct="false" correctSign="" correctSignExceptComma="false" /><value /><JavaScript /></field><field name="AGT_ADDR" type="edit" displayFieldName="주소"><properties height="13.000" width="170.000" x="387.830" y="627.615" /><propertiesEx limitInput="0" backColor="255,255,255" encrypt="false" entry="false" hidden="false" expNum="1" font="굴림" fontColor="0,0,0" fontSize="11" guideLine="" halign="center" inputCtrl="1" mLine="true" maskChar="*" maskType="" maxLength="0" unit="0" readonly="false" valign="middle" correct="false" correctSign="" correctSignExceptComma="false" /><value /><JavaScript /></field><field name="AGT_IDNO" type="edit" displayFieldName="상속인주민등록번호"><properties height="13.000" width="170.000" x="387.830" y="602.115" /><propertiesEx limitInput="0" backColor="255,255,255" encrypt="false" entry="false" hidden="false" expNum="1" font="굴림" fontColor="0,0,0" fontSize="11" guideLine="" halign="center" inputCtrl="3" mLine="true" maskChar="*" maskType="" maxLength="0" unit="0" readonly="false" valign="middle" correct="false" correctSign="" correctSignExceptComma="false" /><value /><JavaScript /></field><field name="AGT_NM" type="edit" displayFieldName="상속인"><properties height="13.000" width="170.000" x="387.830" y="575.865" /><propertiesEx limitInput="0" backColor="255,255,255" encrypt="false" entry="false" hidden="false" expNum="1" font="굴림" fontColor="0,0,0" fontSize="11" guideLine="" halign="center" inputCtrl="1" mLine="true" maskChar="*" maskType="" maxLength="0" unit="0" readonly="false" valign="middle" correct="false" correctSign="" correctSignExceptComma="false" /><value /><JavaScript /></field><field name="CUST_NM" type="edit" displayFieldName="망인"><properties height="15.000" width="75.000" x="217.230" y="499.280" /><propertiesEx limitInput="0" backColor="255,255,255" encrypt="false" entry="false" hidden="false" expNum="1" font="굴림" fontColor="0,0,0" fontSize="11" guideLine="" halign="center" inputCtrl="1" mLine="true" maskChar="*" maskType="" maxLength="0" unit="0" readonly="false" valign="middle" correct="false" correctSign="" correctSignExceptComma="false" /><value /><JavaScript /></field><field name="ACNO" type="edit" displayFieldName="계좌번호"><properties height="15.000" width="90.000" x="345.053" y="499.280" /><propertiesEx limitInput="0" backColor="255,255,255" encrypt="false" entry="false" hidden="false" expNum="1" font="굴림" fontColor="0,0,0" fontSize="11" guideLine="" halign="center" inputCtrl="3" mLine="true" maskChar="*" maskType="" maxLength="0" unit="0" readonly="false" valign="middle" correct="false" correctSign="" correctSignExceptComma="false" /><value /><JavaScript /></field><field name="DCDT" type="edit" displayFieldName="미성년 자녀"><properties height="15.000" width="130.000" x="222.480" y="478.280" /><propertiesEx limitInput="0" backColor="255,255,255" encrypt="false" entry="false" hidden="false" expNum="1" font="굴림" fontColor="0,0,0" fontSize="11" guideLine="" halign="center" inputCtrl="1" mLine="true" maskChar="*" maskType="" maxLength="0" unit="0" readonly="false" valign="middle" correct="false" correctSign="" correctSignExceptComma="false" /><value /><JavaScript /></field><field name="CPNM" type="edit" displayFieldName="종목및수량"><properties height="15.000" width="270.000" x="251.689" y="433.925" /><propertiesEx limitInput="0" backColor="255,255,255" encrypt="false" entry="false" hidden="false" expNum="1" font="굴림" fontColor="0,0,0" fontSize="11" guideLine="" halign="center" inputCtrl="1" mLine="true" maskChar="*" maskType="" maxLength="0" unit="0" readonly="false" valign="middle" correct="false" correctSign="" correctSignExceptComma="false" /><value /><JavaScript /></field><field name="AMUT" type="edit" displayFieldName="예탁금"><properties height="15.000" width="120.000" x="97.958" y="412.335" /><propertiesEx limitInput="0" backColor="255,255,255" encrypt="false" entry="false" hidden="false" expNum="1" font="굴림" fontColor="0,0,0" fontSize="11" guideLine="" halign="center" inputCtrl="1" mLine="true" maskChar="*" maskType="" maxLength="0" unit="0" readonly="false" valign="middle" correct="false" correctSign="" correctSignExceptComma="false" /><value /><JavaScript /></field><field name="DTYY" type="label" displayFieldName="작성년"><properties height="15.000" width="25.000" x="207.065" y="181.923" /><propertiesEx startDate="" endDate="" limitInput="0" backColor="255,255,255" encrypt="false" entry="false" hidden="false" expNum="1" font="굴림" fontColor="0,0,0" fontSize="11" guideLine="" halign="center" inputCtrl="7" mLine="true" maskChar="*" maskType="" maxLength="0" unit="0" readonly="true" valign="middle" correct="false" correctSign="" correctSignExceptComma="false" /><value /><JavaScript /></field><field name="DTMM" type="label" displayFieldName="작성월"><properties height="15.000" width="20.000" x="256.690" y="181.923" /><propertiesEx startDate="" endDate="" limitInput="0" backColor="255,255,255" encrypt="false" entry="false" hidden="false" expNum="1" font="굴림" fontColor="0,0,0" fontSize="11" guideLine="" halign="center" inputCtrl="7" mLine="true" maskChar="*" maskType="" maxLength="0" unit="0" readonly="true" valign="middle" correct="false" correctSign="" correctSignExceptComma="false" /><value /><JavaScript /></field><field name="DTDD" type="label" displayFieldName="작성일"><properties height="15.000" width="20.000" x="315.940" y="181.923" /><propertiesEx startDate="" endDate="" limitInput="0" backColor="255,255,255" encrypt="false" entry="false" hidden="false" expNum="1" font="굴림" fontColor="0,0,0" fontSize="11" guideLine="" halign="center" inputCtrl="7" mLine="true" maskChar="*" maskType="" maxLength="0" unit="0" readonly="true" valign="middle" correct="false" correctSign="" correctSignExceptComma="false" /><value /><JavaScript /></field><field name="P_AGT_NM" type="pen" displayFieldName="상속인"><properties height="25.000" width="100.000" x="384.289" y="122.524" /><propertiesEx limitInput="0" penColor="0,0,0" penWidth="1.000" sync="0" encrypt="false" entry="false" hidden="false" guideLine="" halign="center" inputCtrl="4" maskType="" readonly="false" valign="middle" correct="false" correctSign="" correctSignExceptComma="false" /><value /><JavaScript /></field><field name="AGT_SEAL" type="image" displayFieldName="상속인인감도장"><properties height="50.000" width="50.000" x="484.202" y="109.850" /><propertiesEx limitInput="0" zoom="0" encrypt="false" entry="false" hidden="false" guideLine="" halign="center" inputCtrl="0" maskType="" readonly="false" valign="middle" correct="false" correctSign="" correctSignExceptComma="false" /><value /><JavaScript /></field></page></body><gatherGroups /><rankGroups /><syncFields /><PenSignHandWritingRecogGroups /><infoFields /><PenSignEtcGatherGroups /><zoomGroups /><radioGroups /><tail /></forms>
