<?xml version="1.0" encoding="UTF-8"?>
<forms version="0.4" date="20240510122602" nm="보이스피싱 예방을 위한 문진표" imgfileNames=""><pdf><fileName>30100026.pdf</fileName><totalPage>1</totalPage></pdf><header /><body><page no="1" code="" mustRead="false" title=""><field name="TLNO_Y" type="radio" displayFieldName="직원전화_예"><properties height="14.000" width="23.000" x="457.176" y="556.263" /><propertiesEx limitInput="0" group="1" idx="1" caption="" shape="1" entry="false" hidden="false" guideLine="" halign="center" maskType="" readonly="false" valign="middle" correct="false" correctSign="" correctSignExceptComma="false" /><value /><JavaScript /></field><field name="TLNO_N" type="radio" displayFieldName="직원전화_아니오"><properties height="14.000" width="23.000" x="457.176" y="526.263" /><propertiesEx limitInput="0" group="1" idx="2" caption="" shape="1" encrypt="false" entry="false" hidden="false" guideLine="" halign="center" maskType="" readonly="false" valign="middle" correct="false" correctSign="" correctSignExceptComma="false" /><value /><JavaScript /></field><field name="LOAN_Y" type="radio" displayFieldName="대출_예"><properties height="14.000" width="23.000" x="457.176" y="482.013" /><propertiesEx limitInput="0" group="2" idx="1" caption="" shape="1" encrypt="false" entry="false" hidden="false" guideLine="" halign="center" maskType="" readonly="false" valign="middle" correct="false" correctSign="" correctSignExceptComma="false" /><value /><JavaScript /></field><field name="LOAN_N" type="radio" displayFieldName="대출_아니오"><properties height="14.000" width="23.000" x="457.176" y="454.263" /><propertiesEx limitInput="0" group="2" idx="2" caption="" shape="1" encrypt="false" entry="false" hidden="false" guideLine="" halign="center" maskType="" readonly="false" valign="middle" correct="false" correctSign="" correctSignExceptComma="false" /><value /><JavaScript /></field><field name="CRRT_Y" type="radio" displayFieldName="신용등급_예"><properties height="14.000" width="23.000" x="457.176" y="408.513" /><propertiesEx limitInput="0" group="3" idx="1" caption="" shape="1" encrypt="false" entry="false" hidden="false" guideLine="" halign="center" maskType="" readonly="false" valign="middle" correct="false" correctSign="" correctSignExceptComma="false" /><value /><JavaScript /></field><field name="CRRT_N" type="radio" displayFieldName="신용등급_아니오"><properties height="14.000" width="23.000" x="457.176" y="380.013" /><propertiesEx limitInput="0" group="3" idx="2" caption="" shape="1" encrypt="false" entry="false" hidden="false" guideLine="" halign="center" maskType="" readonly="false" valign="middle" correct="false" correctSign="" correctSignExceptComma="false" /><value /><JavaScript /></field><field name="DT2Y" type="edit" displayFieldName="작성년"><properties height="21.000" width="18.000" x="114.203" y="224.439" /><propertiesEx startDate="" endDate="" limitInput="0" backColor="255,255,255" encrypt="false" entry="false" hidden="false" expNum="1" font="굴림" fontColor="0,0,0" fontSize="11" guideLine="" halign="center" inputCtrl="7" mLine="true" maskChar="*" maskType="" maxLength="0" unit="0" readonly="false" valign="middle" correct="false" correctSign="" correctSignExceptComma="false" /><value /><JavaScript /></field><field name="DTMM" type="edit" displayFieldName="작성월"><properties height="21.000" width="23.000" x="140.735" y="224.439" /><propertiesEx startDate="" endDate="" limitInput="0" backColor="255,255,255" encrypt="false" entry="false" hidden="false" expNum="1" font="굴림" fontColor="0,0,0" fontSize="11" guideLine="" halign="center" inputCtrl="7" mLine="true" maskChar="*" maskType="" maxLength="0" unit="0" readonly="false" valign="middle" correct="false" correctSign="" correctSignExceptComma="false" /><value /><JavaScript /></field><field name="DTDD" type="edit" displayFieldName="작성일"><properties height="21.000" width="23.000" x="175.985" y="224.439" /><propertiesEx startDate="" endDate="" limitInput="0" backColor="255,255,255" encrypt="false" entry="false" hidden="false" expNum="1" font="굴림" fontColor="0,0,0" fontSize="11" guideLine="" halign="center" inputCtrl="7" mLine="true" maskChar="*" maskType="" maxLength="0" unit="0" readonly="false" valign="middle" correct="false" correctSign="" correctSignExceptComma="false" /><value /><JavaScript /></field><field name="P_CUST_NM" type="pen" displayFieldName="고객명"><properties height="22.000" width="110.000" x="358.098" y="229.082" /><propertiesEx limitInput="0" penColor="0,0,0" penWidth="1.000" sync="1" encrypt="false" entry="false" hidden="false" guideLine="" halign="center" inputCtrl="19" maskType="" readonly="false" valign="middle" correct="false" correctSign="" correctSignExceptComma="false" /><value /><JavaScript /></field><field name="T_CUST_NM" type="edit" displayFieldName="고객명(조건)"><properties height="22.000" width="110.000" x="358.100" y="229.100" /><propertiesEx limitInput="0" backColor="255,255,255" encrypt="false" entry="false" hidden="true" expNum="1" font="굴림" fontColor="0,0,0" fontSize="11" guideLine="" halign="center" inputCtrl="1" mLine="true" maskChar="*" maskType="" maxLength="0" unit="0" readonly="false" valign="middle" correct="false" correctSign="" correctSignExceptComma="false" /><value /><JavaScript /></field><field name="P_CUST_SIGN" type="pen" displayFieldName="고객서명"><properties height="22.000" width="60.000" x="468.018" y="229.100" /><propertiesEx limitInput="0" penColor="0,0,0" penWidth="1.000" sync="1" encrypt="false" entry="false" hidden="false" guideLine="" halign="center" inputCtrl="19" maskType="" readonly="false" valign="middle" correct="false" correctSign="" correctSignExceptComma="false" /><value /><JavaScript /></field><field name="P_CUST_SIGN2" type="pen" displayFieldName="고객서명(조건)"><properties height="22.000" width="60.000" x="468.000" y="229.100" /><propertiesEx limitInput="0" penColor="0,0,0" penWidth="1.000" sync="0" encrypt="false" entry="false" hidden="true" guideLine="" halign="center" inputCtrl="8" maskType="" unit="0" readonly="false" valign="middle" correct="false" correctSign="" correctSignExceptComma="false" /><value /><JavaScript /></field><field name="CUST_STP" type="image" displayFieldName="고객도장"><properties height="40.000" width="40.000" x="509.562" y="220.094" /><propertiesEx limitInput="0" zoom="0" encrypt="false" entry="false" hidden="false" guideLine="" halign="center" inputCtrl="12" maskType="" unit="0" readonly="false" valign="middle" correct="false" correctSign="" correctSignExceptComma="false" /><value /><JavaScript /></field></page></body><gatherGroups /><rankGroups /><syncFields><page no="1"><syncField no="1"><signatureField>P_CUST_NM</signatureField><signField>P_CUST_SIGN</signField></syncField></page></syncFields><PenSignHandWritingRecogGroups /><infoFields /><PenSignEtcGatherGroups /><zoomGroups /><radioGroups><radioGroup no="1">RadioGroup1</radioGroup><radioGroup no="2">RadioGroup2</radioGroup><radioGroup no="3">RadioGroup3</radioGroup></radioGroups><tail /></forms>
